spotfm/__init__.py
spotfm/cli.py
spotfm/lastfm.py
spotfm/spotify.py
spotfm/utils.py
spotfm-0.0.4.dist-info/LICENSE
spotfm-0.0.4.dist-info/METADATA
spotfm-0.0.4.dist-info/WHEEL
spotfm-0.0.4.dist-info/entry_points.txt
spotfm-0.0.4.dist-info/top_level.txt
spotfm-0.0.4.dist-info/RECORD
