Metadata-Version: 2.1
Name: spotfm
Version: 0.0.4
Summary: Simple Python lib to interact with Spotify and Last.FM APIs
Author-email: Julien Mailleret <julien@mailleret.fr>
License: MIT License
Project-URL: homepage, https://github.com/jmlrt/spotfm
Requires-Python: >=3.11
License-File: LICENSE
Requires-Dist: pylast
Requires-Dist: spotipy
Provides-Extra: dev
Requires-Dist: ipython ; extra == 'dev'
Requires-Dist: pre-commit ; extra == 'dev'
Requires-Dist: twine ; extra == 'dev'
